joblib_htcondor/__init__.py
joblib_htcondor/_version.py
joblib_htcondor/backend.py
joblib_htcondor/delayed_submission.py
joblib_htcondor/executor.py
joblib_htcondor/logging.py
joblib_htcondor/tests/test_backend.py
joblib_htcondor/tests/test_delayed_submission.py
joblib_htcondor/tests/test_runtime.py
joblib_htcondor/ui/__main__.py
joblib_htcondor/ui/config.py
joblib_htcondor/ui/main_window.py
joblib_htcondor/ui/monitor.py
joblib_htcondor/ui/open_window.py
joblib_htcondor/ui/treeparser.py
joblib_htcondor/ui/uilogging.py
joblib_htcondor/ui/utils.py
joblib_htcondor/ui/window.py
joblib_htcondor-0.2.1.dist-info/licenses/LICENSE
joblib_htcondor-0.2.1.dist-info/METADATA
joblib_htcondor-0.2.1.dist-info/WHEEL
joblib_htcondor-0.2.1.dist-info/top_level.txt
joblib_htcondor-0.2.1.dist-info/RECORD
