Metadata-Version: 2.4
Name: joblib_htcondor
Version: 0.2.1
Summary: Joblib HTCondor Backend
Author-email: Synchon Mandal <s.mandal@fz-juelich.de>, Fede Raimondo <f.raimondo@fz-juelich.de>
Maintainer-email: Synchon Mandal <s.mandal@fz-juelich.de>, Fede Raimondo <f.raimondo@fz-juelich.de>
License: AGPL-3.0-only
Project-URL: Source, https://github.com/juaml/joblib-htcondor
Classifier: Development Status :: 4 - Beta
Classifier: Environment :: Console
Classifier: Intended Audience :: Developers
Classifier: Intended Audience :: Science/Research
Classifier: Intended Audience :: Education
Classifier: License :: OSI Approved :: BSD License
Classifier: Operating System :: OS Independent
Classifier: Programming Language :: Python :: 3
Classifier: Programming Language :: Python :: 3.9
Classifier: Programming Language :: Python :: 3.10
Classifier: Programming Language :: Python :: 3.11
Classifier: Programming Language :: Python :: 3.12
Classifier: Programming Language :: Python :: 3.13
Classifier: Topic :: Scientific/Engineering
Classifier: Topic :: Utilities
Classifier: Topic :: Software Development :: Libraries
Requires-Python: >=3.9
License-File: LICENSE
Requires-Dist: joblib==1.4.2
Requires-Dist: htcondor<24.0.0,>=23.0.0
Requires-Dist: flufl.lock==8.1.0
Provides-Extra: dev
Requires-Dist: tox; extra == "dev"
Requires-Dist: pre-commit; extra == "dev"
Requires-Dist: ruff; extra == "dev"
Requires-Dist: towncrier; extra == "dev"
Dynamic: license-file
